ethiopian_date_converter/__init__.py
ethiopian_date_converter/constants.py
ethiopian_date_converter/converter.py
ethiopian_date_converter/date_classes.py
ethiopian_date_converter/utils.py
ethiopian_date_converter/core/ethiopic_calendar.c
ethiopian_date_converter/core/ethiopic_calendar.h
tests/__init__.py
tests/test_converter.py
tests/test_date_classes.py
ethiopian_date_converter_py-1.0.0.dist-info/METADATA
ethiopian_date_converter_py-1.0.0.dist-info/WHEEL
ethiopian_date_converter_py-1.0.0.dist-info/top_level.txt
ethiopian_date_converter_py-1.0.0.dist-info/RECORD
