Metadata-Version: 2.4
Name: ethiopian-date-converter-py
Version: 1.0.0
Summary: Ethiopian calendar date conversion for Python
Home-page: https://github.com/abiywondimu5758/ethiopian-date-converter
Author: Abiy
Author-email: Abiy <abiywondimu1@gmail.com>
License: MIT
Project-URL: Homepage, https://github.com/abiywondimu5758/ethiopian-date-converter
Project-URL: Documentation, https://github.com/abiywondimu5758/ethiopian-date-converter/tree/main/docs/python
Project-URL: Repository, https://github.com/abiywondimu5758/ethiopian-date-converter
Project-URL: Bug Reports, https://github.com/abiywondimu5758/ethiopian-date-converter/issues
Keywords: ethiopian,calendar,date,conversion,gregorian,geez,python,datetime,ethiopia,amharic
Classifier: Development Status :: 5 - Production/Stable
Classifier: Intended Audience :: Developers
Classifier: License :: OSI Approved :: MIT License
Classifier: Operating System :: OS Independent
Classifier: Programming Language :: Python :: 3
Classifier: Programming Language :: Python :: 3.7
Classifier: Programming Language :: Python :: 3.8
Classifier: Programming Language :: Python :: 3.9
Classifier: Programming Language :: Python :: 3.10
Classifier: Programming Language :: Python :: 3.11
Classifier: Programming Language :: Python :: 3.12
Classifier: Programming Language :: C
Classifier: Topic :: Software Development :: Libraries :: Python Modules
Classifier: Topic :: Scientific/Engineering :: Astronomy
Classifier: Topic :: Office/Business :: Scheduling
Requires-Python: >=3.7
Provides-Extra: dev
Requires-Dist: pytest>=6.0; extra == "dev"
Requires-Dist: pytest-cov>=2.0; extra == "dev"
Requires-Dist: black>=21.0; extra == "dev"
Requires-Dist: flake8>=3.8; extra == "dev"
Requires-Dist: mypy>=0.800; extra == "dev"
Dynamic: author
Dynamic: home-page
Dynamic: requires-python
